configurations/__init__.py
configurations/config.py
run/__init__.py
run/run.py
utilities/__init__.py
utilities/user_input_file.py
weather_api/WeatherAPI.py
weather_api/__init__.py
weatherapplicationarorarajat-0.0.4.dist-info/LICENSE
weatherapplicationarorarajat-0.0.4.dist-info/METADATA
weatherapplicationarorarajat-0.0.4.dist-info/WHEEL
weatherapplicationarorarajat-0.0.4.dist-info/top_level.txt
weatherapplicationarorarajat-0.0.4.dist-info/RECORD
